MANIFEST.in
setup.cfg
setup.py
bootalchemy/__init__.py
bootalchemy/converters.py
bootalchemy/loader.py
bootalchemy.egg-info/PKG-INFO
bootalchemy.egg-info/SOURCES.txt
bootalchemy.egg-info/dependency_links.txt
bootalchemy.egg-info/entry_points.txt
bootalchemy.egg-info/requires.txt
bootalchemy.egg-info/top_level.txt
bootalchemy.egg-info/zip-safe
docs/boottoot.py
docs/html/genindex.html
docs/html/index.html
docs/html/objects.inv
docs/html/search.html
docs/html/searchindex.js
docs/html/.doctrees/environment.pickle
docs/html/.doctrees/index.doctree
docs/html/_sources/index.txt
docs/html/_static/contents.png
docs/html/_static/default.css
docs/html/_static/doctools.js
docs/html/_static/file.png
docs/html/_static/jquery.js
docs/html/_static/minus.png
docs/html/_static/navigation.png
docs/html/_static/plus.png
docs/html/_static/pygments.css
docs/html/_static/rightsidebar.css
docs/html/_static/searchtools.js
docs/html/_static/sphinxdoc.css
docs/html/_static/stickysidebar.css
docs/html/_static/traditional.css
docs/source/conf.py
docs/source/index.rst