Metadata-Version: 1.0
Name: bootalchemy
Version: 0.4
Summary: A package to create database entries from yaml using sqlalchemy.
Home-page: UNKNOWN
Author: Christopher Perkins
Author-email: chris@percious.com
License: MIT
Platform: UNKNOWN
